<?xml version="1.0" encoding="UTF-8"?>
<GameData>
    <!-- 游戏角色列表 -->
    <Characters>
        <Character id="1">
            <Name>勇士</Name>
            <Level>10</Level>
            <Health>100</Health>
            <Mana>50</Mana>
            <Class>Warrior</Class>
        </Character>
        <Character id="2">
            <Name>法师</Name>
            <Level>8</Level>
            <Health>60</Health>
            <Mana>120</Mana>
            <Class>Mage</Class>
        </Character>
        <Character id="3">
            <Name>弓箭手</Name>
            <Level>9</Level>
            <Health>80</Health>
            <Mana>40</Mana>
            <Class>Archer</Class>
        </Character>
    </Characters>

    <!-- 游戏设置 -->
    <Settings>
        <MusicVolume>0.8</MusicVolume>
        <SFXVolume>0.6</SFXVolume>
        <Resolution width="1920" height="1080" fullscreen="true"/>
    </Settings>
</GameData>
